dbt/__init__.py
dbt/adapters/redshift/__init__.py
dbt/adapters/redshift/__version__.py
dbt/adapters/redshift/auth_providers.py
dbt/adapters/redshift/connections.py
dbt/adapters/redshift/impl.py
dbt/adapters/redshift/relation.py
dbt/adapters/redshift/utility.py
dbt/adapters/redshift/relation_configs/__init__.py
dbt/adapters/redshift/relation_configs/base.py
dbt/adapters/redshift/relation_configs/dist.py
dbt/adapters/redshift/relation_configs/materialized_view.py
dbt/adapters/redshift/relation_configs/policies.py
dbt/adapters/redshift/relation_configs/sort.py
dbt/include/redshift/__init__.py
dbt/include/redshift/dbt_project.yml
dbt/include/redshift/profile_template.yml
dbt/include/redshift/macros/adapters.sql
dbt/include/redshift/macros/relations.sql
dbt/include/redshift/macros/timestamps.sql
dbt/include/redshift/macros/adapters/apply_grants.sql
dbt/include/redshift/macros/adapters/unit_testing.sql
dbt/include/redshift/macros/catalog/by_relation.sql
dbt/include/redshift/macros/catalog/by_schema.sql
dbt/include/redshift/macros/catalog/catalog.sql
dbt/include/redshift/macros/materializations/incremental_delete_insert.sql
dbt/include/redshift/macros/materializations/incremental_merge.sql
dbt/include/redshift/macros/materializations/materialized_view.sql
dbt/include/redshift/macros/materializations/snapshot_merge.sql
dbt/include/redshift/macros/materializations/table.sql
dbt/include/redshift/macros/materializations/view.sql
dbt/include/redshift/macros/materializations/functions/scalar.sql
dbt/include/redshift/macros/materializations/seeds/helpers.sql
dbt/include/redshift/macros/metadata/relation_last_modified.sql
dbt/include/redshift/macros/relations/materialized_view/alter.sql
dbt/include/redshift/macros/relations/materialized_view/create.sql
dbt/include/redshift/macros/relations/materialized_view/describe.sql
dbt/include/redshift/macros/relations/materialized_view/drop.sql
dbt/include/redshift/macros/relations/materialized_view/refresh.sql
dbt_redshift-1.10.0.dist-info/METADATA
dbt_redshift-1.10.0.dist-info/WHEEL
dbt_redshift-1.10.0.dist-info/licenses/LICENSE
dbt_redshift-1.10.0.dist-info/RECORD
