Metadata-Version: 2.4
Name: dbt-redshift
Version: 1.10.0
Summary: The Redshift adapter plugin for dbt
Project-URL: Homepage, https://github.com/dbt-labs/dbt-adapters/tree/main/dbt-redshift
Project-URL: Documentation, https://docs.getdbt.com
Project-URL: Repository, https://github.com/dbt-labs/dbt-adapters.git#subdirectory=dbt-redshift
Project-URL: Issues, https://github.com/dbt-labs/dbt-adapters/issues
Project-URL: Changelog, https://github.com/dbt-labs/dbt-adapters/blob/main/dbt-redshift/CHANGELOG.md
Author-email: dbt Labs <info@dbtlabs.com>
Maintainer-email: dbt Labs <info@dbtlabs.com>
License-File: LICENSE
Keywords: adapter,adapters,amazon,amazon web services,aws,database,dbt,dbt Cloud,dbt Core,dbt Labs,dbt-core,elt,redshift
Classifier: Development Status :: 5 - Production/Stable
Classifier: License :: OSI Approved :: Apache Software License
Classifier: Operating System :: MacOS :: MacOS X
Classifier: Operating System :: Microsoft :: Windows
Classifier: Operating System :: POSIX :: Linux
Classifier: Programming Language :: Python :: 3.10
Classifier: Programming Language :: Python :: 3.11
Classifier: Programming Language :: Python :: 3.12
Classifier: Programming Language :: Python :: 3.13
Requires-Python: >=3.10.0
Requires-Dist: agate
Requires-Dist: dbt-adapters<2.0,>=1.19.0
Requires-Dist: dbt-common<2.0,>=1.10
Requires-Dist: dbt-core>=1.8.0b3
Requires-Dist: dbt-postgres<2.0,>=1.10.0rc1
Requires-Dist: redshift-connector<2.2,>=2.1.8
Requires-Dist: requests
Requires-Dist: sqlparse<0.6.0,>=0.5.0
